LICENSE
README.md
setup.py
rustkit/__init__.py
rustkit/error.py
rustkit/option.py
rustkit/result.py
rustkit.egg-info/PKG-INFO
rustkit.egg-info/SOURCES.txt
rustkit.egg-info/dependency_links.txt
rustkit.egg-info/top_level.txt