Metadata-Version: 2.1
Name: rustkit
Version: 0.0.2
Summary: A Rust toolkit library for python which allows you to write rust-like code in python.
Home-page: https://github.com/ddjerqq/rustkit
Author: ddjerqq
Author-email: ddjerqq@gmail.com
License: GNU
Keywords: rust optional result iterator vector
Platform: UNKNOWN
License-File: LICENSE
